LICENSE
MANIFEST.in
README.txt
requirements.txt
setup.py
examples/gf-machine-emulator.cfg.sample
examples/gf-machine-emulator.py
gfutilities/__init__.py
gfutilities/_common.py
gfutilities/configuration.py
gfutilities.egg-info/PKG-INFO
gfutilities.egg-info/SOURCES.txt
gfutilities.egg-info/dependency_links.txt
gfutilities.egg-info/top_level.txt
gfutilities/device/__init__.py
gfutilities/device/basemachine.py
gfutilities/device/emulator.py
gfutilities/device/settings.py
gfutilities/puls/__init__.py
gfutilities/puls/pulsedata.py
gfutilities/service/__init__.py
gfutilities/service/authentication.py
gfutilities/service/gfuiservice.py
gfutilities/service/websocket.py