Metadata-Version: 1.1
Name: gfutilities
Version: 0.8.4
Summary: Glowforge Utilities
Home-page: https://github.com/ScottW514/Glowforge-Utilities
Author: Scott Wiederhold
Author-email: s.e.wiederhold@gmail.com
License: MIT
Keywords: Glowforge OpenGlow
Platform: UNKNOWN
Classifier: Development Status :: 4 - Beta
Classifier: Intended Audience :: Developers
Classifier: License :: OSI Approved :: MIT License
Classifier: Programming Language :: Python
Classifier: Programming Language :: Python :: 3.7
Classifier: Operating System :: MacOS :: MacOS X
Classifier: Operating System :: Microsoft :: Windows
Classifier: Operating System :: POSIX :: Linux
Classifier: Topic :: Software Development :: Embedded Systems
